WLedController
